setup.py
idol/LICENSE
idol/README
idol/VERSION
idol/__idol__.py
idol/__idol_mar__.py
idol/__init__.py
idol/build_env.py
idol/cli.py
idol/functional.py
idol/generator.py
idol/idol_dataclass
idol/idol_dataclass.py
idol/idol_mar
idol/idol_mar.py
idol/idol_py
idol/idol_py.py
idol/scripter.py
idol.egg-info/PKG-INFO
idol.egg-info/SOURCES.txt
idol.egg-info/dependency_links.txt
idol.egg-info/not-zip-safe
idol.egg-info/requires.txt
idol.egg-info/top_level.txt
idol/py/codegen/__idol__.py
idol/py/codegen/__init__.py
idol/py/codegen/schema/__init__.py
idol/py/codegen/schema/field.py
idol/py/codegen/schema/literal.py
idol/py/codegen/schema/module.py
idol/py/codegen/schema/primitive_type.py
idol/py/codegen/schema/reference.py
idol/py/codegen/schema/struct_kind.py
idol/py/codegen/schema/type.py
idol/py/codegen/schema/type_struct.py
idol/py/schema/__init__.py
idol/py/schema/dependency.py
idol/py/schema/field.py
idol/py/schema/literal.py
idol/py/schema/module.py
idol/py/schema/primitive_type.py
idol/py/schema/reference.py
idol/py/schema/struct_kind.py
idol/py/schema/type.py
idol/py/schema/type_struct.py