Metadata-Version: 1.0
Name: idol
Version: 0.5.12
Summary: idol codegen library tools
Home-page: http://github.com/lyric-com/idol
Author: Zach Collins
Author-email: zach.collins@lyric.com
License: MIT
Platform: UNKNOWN
